Metadata-Version: 2.1
Name: pynvi
Version: 0.1.0rc2
Summary: pynvi Türkiye Cumhuriyeti Nüfus ve Vatandaşlık İşleri Genel Müdürlüğü SOAP servisi için köprü bir Python kütüphanesidir.
Home-page: https://github.com/erayerdin/pynvi
Author: Eray Erdin
Author-email: eraygezer.94@gmail.com
License: Apache License 2.0
Download-URL: https://github.com/erayerdin/pynvi/archive/master.zip
Keywords: pynvi nvi nüfus vatandaşlık işleri türkiye
Platform: UNKNOWN
Classifier: Development Status :: 2 - Pre-Alpha
Classifier: Intended Audience :: Developers
Classifier: License :: OSI Approved :: Apache Software License
Classifier: Programming Language :: Python :: 3 :: Only
Classifier: Programming Language :: Python :: 3.5
Classifier: Programming Language :: Python :: 3.6
Classifier: Programming Language :: Python :: 3.7
Classifier: Topic :: Software Development
